needle/__init__.py
needle/cases.py
needle/driver.py
needle/plugin.py
needle/engines/__init__.py
needle/engines/base.py
needle/engines/imagemagick_engine.py
needle/engines/perceptualdiff_engine.py
needle/engines/pil_engine.py
needle/js/__init__.py
needle/js/__init__.pyc
needle/js/jquery-1.11.0.min.js
needle-0.4.1.dist-info/DESCRIPTION.rst
needle-0.4.1.dist-info/METADATA
needle-0.4.1.dist-info/RECORD
needle-0.4.1.dist-info/WHEEL
needle-0.4.1.dist-info/entry_points.txt
needle-0.4.1.dist-info/metadata.json
needle-0.4.1.dist-info/top_level.txt
